maistro_csv_tool/__init__.py
maistro_csv_tool/tool.py
maistro_csv_tool-1.0.1.dist-info/licenses/LICENSE
maistro_csv_tool-1.0.1.dist-info/METADATA
maistro_csv_tool-1.0.1.dist-info/WHEEL
maistro_csv_tool-1.0.1.dist-info/top_level.txt
maistro_csv_tool-1.0.1.dist-info/RECORD
