Metadata-Version: 2.4
Name: maistro-csv-tool
Version: 1.0.1
Summary: CSV dosyalarını okuyan/yazan, JSON ile etkileşen basit bir yardımcı araç
Author-email: Mine Korkmaz <rminekorkmaz@gmail.com>
License: MIT
Project-URL: Homepage, https://example.com/csv_tool
Project-URL: Repository, https://example.com/csv_tool/repo
Requires-Python: >=3.9
License-File: LICENSE
Requires-Dist: maistro-sdk>=1.6.0
Provides-Extra: dev
Requires-Dist: pytest>=7.4; extra == "dev"
Requires-Dist: build; extra == "dev"
Requires-Dist: twine; extra == "dev"
Dynamic: license-file
